lazyedabf/__init__.py
lazyedabf/archivo.py
lazyedabf/dataframe.py
lazyedabf/masivo.py
lazyedabf/data_loader/__init__.py
lazyedabf/data_loader/eda_loader.py
lazyedabf/utils/__init__.py
lazyedabf/utils/data_validation.py
lazyedabf/utils/dataframe_operations.py
lazyedabf/utils/excel_export.py
lazyedabf-1.0.3.dist-info/METADATA
lazyedabf-1.0.3.dist-info/WHEEL
lazyedabf-1.0.3.dist-info/top_level.txt
lazyedabf-1.0.3.dist-info/RECORD
