Metadata-Version: 2.4
Name: lazyedabf
Version: 1.0.3
Summary: A package for EDA on CSV, Parquet.
Author: nicolas_conde_brainfood
Requires-Python: >=3.7
Requires-Dist: pandas==2.2.2
Requires-Dist: polars==1.10.0
Requires-Dist: XlsxWriter==3.2.0
Requires-Dist: pyarrow==17.0.0
Requires-Dist: tqdm
Dynamic: author
Dynamic: description
Dynamic: description-content-type
Dynamic: requires-dist
Dynamic: requires-python
Dynamic: summary
